cc_bitkub/__init__.py
cc_bitkub/cc_bitkub.py
cc_bitkub_Chetchaiyan-0.0.5.dist-info/LICENSE
cc_bitkub_Chetchaiyan-0.0.5.dist-info/METADATA
cc_bitkub_Chetchaiyan-0.0.5.dist-info/WHEEL
cc_bitkub_Chetchaiyan-0.0.5.dist-info/top_level.txt
cc_bitkub_Chetchaiyan-0.0.5.dist-info/RECORD
