Metadata-Version: 2.1
Name: cc-bitkub-Chetchaiyan
Version: 0.0.5
Summary: bitkub exchange connector in ccxt style
Home-page: https://chetchaiyan.com/
Author: Chet Chetchaiyan
Author-email: Chetchaiyan@gmail.com
License: UNKNOWN
Project-URL: Bug Tracker, https://chetchaiyan.com/
Platform: UNKNOWN
Classifier: Programming Language :: Python :: 3
Classifier: License :: OSI Approved :: MIT License
Classifier: Operating System :: OS Independent
Requires-Python: >=3.8
License-File: LICENSE
